{"nodes": [{"id": "d_plant_pulse_fyp_lib_services_local_db_service_dart", "label": "local_db_service.dart", "file_type": "code", "source_file": "D:\\Plant Pulse FYP\\lib\\services\\local_db_service.dart", "source_location": null}, {"id": "d_plant_pulse_fyp_lib_services_local_db_service_dart_localdbservice", "label": "LocalDbService", "file_type": "code", "source_file": "D:\\Plant Pulse FYP\\lib\\services\\local_db_service.dart", "source_location": null}, {"id": "d_plant_pulse_fyp_lib_services_local_db_service_dart_opendatabase", "label": "openDatabase", "file_type": "code", "source_file": "D:\\Plant Pulse FYP\\lib\\services\\local_db_service.dart", "source_location": null}, {"id": "d_plant_pulse_fyp_lib_services_local_db_service_dart_scans", "label": "scans", "file_type": "code", "source_file": "D:\\Plant Pulse FYP\\lib\\services\\local_db_service.dart", "source_location": null}, {"id": "package_sqflite_sqflite_dart", "label": "package:sqflite/sqflite.dart", "file_type": "code", "source_file": "D:\\Plant Pulse FYP\\lib\\services\\local_db_service.dart", "source_location": null}, {"id": "package_path_path_dart", "label": "package:path/path.dart", "file_type": "code", "source_file": "D:\\Plant Pulse FYP\\lib\\services\\local_db_service.dart", "source_location": null}], "edges": [{"source": "d_plant_pulse_fyp_lib_services_local_db_service_dart", "target": "d_plant_pulse_fyp_lib_services_local_db_service_dart_localdbservice", "relation": "defines", "confidence": "EXTRACTED", "confidence_score": 1.0, "source_file": "D:\\Plant Pulse FYP\\lib\\services\\local_db_service.dart", "source_location": null, "weight": 1.0}, {"source": "d_plant_pulse_fyp_lib_services_local_db_service_dart", "target": "d_plant_pulse_fyp_lib_services_local_db_service_dart_opendatabase", "relation": "defines", "confidence": "EXTRACTED", "confidence_score": 1.0, "source_file": "D:\\Plant Pulse FYP\\lib\\services\\local_db_service.dart", "source_location": null, "weight": 1.0}, {"source": "d_plant_pulse_fyp_lib_services_local_db_service_dart", "target": "d_plant_pulse_fyp_lib_services_local_db_service_dart_scans", "relation": "defines", "confidence": "EXTRACTED", "confidence_score": 1.0, "source_file": "D:\\Plant Pulse FYP\\lib\\services\\local_db_service.dart", "source_location": null, "weight": 1.0}, {"source": "d_plant_pulse_fyp_lib_services_local_db_service_dart", "target": "package_sqflite_sqflite_dart", "relation": "imports", "confidence": "EXTRACTED", "confidence_score": 1.0, "source_file": "D:\\Plant Pulse FYP\\lib\\services\\local_db_service.dart", "source_location": null, "weight": 1.0}, {"source": "d_plant_pulse_fyp_lib_services_local_db_service_dart", "target": "package_path_path_dart", "relation": "imports", "confidence": "EXTRACTED", "confidence_score": 1.0, "source_file": "D:\\Plant Pulse FYP\\lib\\services\\local_db_service.dart", "source_location": null, "weight": 1.0}]}