{"nodes": [{"id": "d_plant_pulse_fyp_lib_widgets_weather_header_dart", "label": "weather_header.dart", "file_type": "code", "source_file": "D:\\Plant Pulse FYP\\lib\\widgets\\weather_header.dart", "source_location": null}, {"id": "d_plant_pulse_fyp_lib_widgets_weather_header_dart_weatherheader", "label": "WeatherHeader", "file_type": "code", "source_file": "D:\\Plant Pulse FYP\\lib\\widgets\\weather_header.dart", "source_location": null}, {"id": "d_plant_pulse_fyp_lib_widgets_weather_header_dart_weatherheaderstate", "label": "_WeatherHeaderState", "file_type": "code", "source_file": "D:\\Plant Pulse FYP\\lib\\widgets\\weather_header.dart", "source_location": null}, {"id": "d_plant_pulse_fyp_lib_widgets_weather_header_dart_initstate", "label": "initState", "file_type": "code", "source_file": "D:\\Plant Pulse FYP\\lib\\widgets\\weather_header.dart", "source_location": null}, {"id": "d_plant_pulse_fyp_lib_widgets_weather_header_dart_build", "label": "build", "file_type": "code", "source_file": "D:\\Plant Pulse FYP\\lib\\widgets\\weather_header.dart", "source_location": null}, {"id": "d_plant_pulse_fyp_lib_widgets_weather_header_dart_buildloading", "label": "_buildLoading", "file_type": "code", "source_file": "D:\\Plant Pulse FYP\\lib\\widgets\\weather_header.dart", "source_location": null}, {"id": "d_plant_pulse_fyp_lib_widgets_weather_header_dart_buildweathercard", "label": "_buildWeatherCard", "file_type": "code", "source_file": "D:\\Plant Pulse FYP\\lib\\widgets\\weather_header.dart", "source_location": null}, {"id": "d_plant_pulse_fyp_lib_widgets_weather_header_dart_container", "label": "Container", "file_type": "code", "source_file": "D:\\Plant Pulse FYP\\lib\\widgets\\weather_header.dart", "source_location": null}, {"id": "d_plant_pulse_fyp_lib_widgets_weather_header_dart_color", "label": "Color", "file_type": "code", "source_file": "D:\\Plant Pulse FYP\\lib\\widgets\\weather_header.dart", "source_location": null}, {"id": "d_plant_pulse_fyp_lib_widgets_weather_header_dart_sizedbox", "label": "SizedBox", "file_type": "code", "source_file": "D:\\Plant Pulse FYP\\lib\\widgets\\weather_header.dart", "source_location": null}, {"id": "d_plant_pulse_fyp_lib_widgets_weather_header_dart_buildagrialert", "label": "_buildAgriAlert", "file_type": "code", "source_file": "D:\\Plant Pulse FYP\\lib\\widgets\\weather_header.dart", "source_location": null}, {"id": "d_plant_pulse_fyp_lib_widgets_weather_header_dart_getweathericon", "label": "_getWeatherIcon", "file_type": "code", "source_file": "D:\\Plant Pulse FYP\\lib\\widgets\\weather_header.dart", "source_location": null}, {"id": "d_plant_pulse_fyp_lib_widgets_weather_header_dart_icon", "label": "Icon", "file_type": "code", "source_file": "D:\\Plant Pulse FYP\\lib\\widgets\\weather_header.dart", "source_location": null}, {"id": "d_plant_pulse_fyp_lib_widgets_weather_header_dart_riskitem", "label": "_riskItem", "file_type": "code", "source_file": "D:\\Plant Pulse FYP\\lib\\widgets\\weather_header.dart", "source_location": null}, {"id": "d_plant_pulse_fyp_lib_widgets_weather_header_dart_column", "label": "Column", "file_type": "code", "source_file": "D:\\Plant Pulse FYP\\lib\\widgets\\weather_header.dart", "source_location": null}, {"id": "dart_ui", "label": "dart:ui", "file_type": "code", "source_file": "D:\\Plant Pulse FYP\\lib\\widgets\\weather_header.dart", "source_location": null}, {"id": "package_flutter_material_dart", "label": "package:flutter/material.dart", "file_type": "code", "source_file": "D:\\Plant Pulse FYP\\lib\\widgets\\weather_header.dart", "source_location": null}, {"id": "package_provider_provider_dart", "label": "package:provider/provider.dart", "file_type": "code", "source_file": "D:\\Plant Pulse FYP\\lib\\widgets\\weather_header.dart", "source_location": null}, {"id": "package_intl_intl_dart", "label": "package:intl/intl.dart", "file_type": "code", "source_file": "D:\\Plant Pulse FYP\\lib\\widgets\\weather_header.dart", "source_location": null}, {"id": "providers_weather_provider_dart", "label": "../providers/weather_provider.dart", "file_type": "code", "source_file": "D:\\Plant Pulse FYP\\lib\\widgets\\weather_header.dart", "source_location": null}, {"id": "models_weather_data_dart", "label": "../models/weather_data.dart", "file_type": "code", "source_file": "D:\\Plant Pulse FYP\\lib\\widgets\\weather_header.dart", "source_location": null}, {"id": "utils_rice_health_logic_dart", "label": "../utils/rice_health_logic.dart", "file_type": "code", "source_file": "D:\\Plant Pulse FYP\\lib\\widgets\\weather_header.dart", "source_location": null}], "edges": [{"source": "d_plant_pulse_fyp_lib_widgets_weather_header_dart", "target": "d_plant_pulse_fyp_lib_widgets_weather_header_dart_weatherheader", "relation": "defines", "confidence": "EXTRACTED", "confidence_score": 1.0, "source_file": "D:\\Plant Pulse FYP\\lib\\widgets\\weather_header.dart", "source_location": null, "weight": 1.0}, {"source": "d_plant_pulse_fyp_lib_widgets_weather_header_dart", "target": "d_plant_pulse_fyp_lib_widgets_weather_header_dart_weatherheaderstate", "relation": "defines", "confidence": "EXTRACTED", "confidence_score": 1.0, "source_file": "D:\\Plant Pulse FYP\\lib\\widgets\\weather_header.dart", "source_location": null, "weight": 1.0}, {"source": "d_plant_pulse_fyp_lib_widgets_weather_header_dart", "target": "d_plant_pulse_fyp_lib_widgets_weather_header_dart_initstate", "relation": "defines", "confidence": "EXTRACTED", "confidence_score": 1.0, "source_file": "D:\\Plant Pulse FYP\\lib\\widgets\\weather_header.dart", "source_location": null, "weight": 1.0}, {"source": "d_plant_pulse_fyp_lib_widgets_weather_header_dart", "target": "d_plant_pulse_fyp_lib_widgets_weather_header_dart_build", "relation": "defines", "confidence": "EXTRACTED", "confidence_score": 1.0, "source_file": "D:\\Plant Pulse FYP\\lib\\widgets\\weather_header.dart", "source_location": null, "weight": 1.0}, {"source": "d_plant_pulse_fyp_lib_widgets_weather_header_dart", "target": "d_plant_pulse_fyp_lib_widgets_weather_header_dart_buildloading", "relation": "defines", "confidence": "EXTRACTED", "confidence_score": 1.0, "source_file": "D:\\Plant Pulse FYP\\lib\\widgets\\weather_header.dart", "source_location": null, "weight": 1.0}, {"source": "d_plant_pulse_fyp_lib_widgets_weather_header_dart", "target": "d_plant_pulse_fyp_lib_widgets_weather_header_dart_buildweathercard", "relation": "defines", "confidence": "EXTRACTED", "confidence_score": 1.0, "source_file": "D:\\Plant Pulse FYP\\lib\\widgets\\weather_header.dart", "source_location": null, "weight": 1.0}, {"source": "d_plant_pulse_fyp_lib_widgets_weather_header_dart", "target": "d_plant_pulse_fyp_lib_widgets_weather_header_dart_container", "relation": "defines", "confidence": "EXTRACTED", "confidence_score": 1.0, "source_file": "D:\\Plant Pulse FYP\\lib\\widgets\\weather_header.dart", "source_location": null, "weight": 1.0}, {"source": "d_plant_pulse_fyp_lib_widgets_weather_header_dart", "target": "d_plant_pulse_fyp_lib_widgets_weather_header_dart_color", "relation": "defines", "confidence": "EXTRACTED", "confidence_score": 1.0, "source_file": "D:\\Plant Pulse FYP\\lib\\widgets\\weather_header.dart", "source_location": null, "weight": 1.0}, {"source": "d_plant_pulse_fyp_lib_widgets_weather_header_dart", "target": "d_plant_pulse_fyp_lib_widgets_weather_header_dart_sizedbox", "relation": "defines", "confidence": "EXTRACTED", "confidence_score": 1.0, "source_file": "D:\\Plant Pulse FYP\\lib\\widgets\\weather_header.dart", "source_location": null, "weight": 1.0}, {"source": "d_plant_pulse_fyp_lib_widgets_weather_header_dart", "target": "d_plant_pulse_fyp_lib_widgets_weather_header_dart_buildagrialert", "relation": "defines", "confidence": "EXTRACTED", "confidence_score": 1.0, "source_file": "D:\\Plant Pulse FYP\\lib\\widgets\\weather_header.dart", "source_location": null, "weight": 1.0}, {"source": "d_plant_pulse_fyp_lib_widgets_weather_header_dart", "target": "d_plant_pulse_fyp_lib_widgets_weather_header_dart_getweathericon", "relation": "defines", "confidence": "EXTRACTED", "confidence_score": 1.0, "source_file": "D:\\Plant Pulse FYP\\lib\\widgets\\weather_header.dart", "source_location": null, "weight": 1.0}, {"source": "d_plant_pulse_fyp_lib_widgets_weather_header_dart", "target": "d_plant_pulse_fyp_lib_widgets_weather_header_dart_icon", "relation": "defines", "confidence": "EXTRACTED", "confidence_score": 1.0, "source_file": "D:\\Plant Pulse FYP\\lib\\widgets\\weather_header.dart", "source_location": null, "weight": 1.0}, {"source": "d_plant_pulse_fyp_lib_widgets_weather_header_dart", "target": "d_plant_pulse_fyp_lib_widgets_weather_header_dart_riskitem", "relation": "defines", "confidence": "EXTRACTED", "confidence_score": 1.0, "source_file": "D:\\Plant Pulse FYP\\lib\\widgets\\weather_header.dart", "source_location": null, "weight": 1.0}, {"source": "d_plant_pulse_fyp_lib_widgets_weather_header_dart", "target": "d_plant_pulse_fyp_lib_widgets_weather_header_dart_column", "relation": "defines", "confidence": "EXTRACTED", "confidence_score": 1.0, "source_file": "D:\\Plant Pulse FYP\\lib\\widgets\\weather_header.dart", "source_location": null, "weight": 1.0}, {"source": "d_plant_pulse_fyp_lib_widgets_weather_header_dart", "target": "dart_ui", "relation": "imports", "confidence": "EXTRACTED", "confidence_score": 1.0, "source_file": "D:\\Plant Pulse FYP\\lib\\widgets\\weather_header.dart", "source_location": null, "weight": 1.0}, {"source": "d_plant_pulse_fyp_lib_widgets_weather_header_dart", "target": "package_flutter_material_dart", "relation": "imports", "confidence": "EXTRACTED", "confidence_score": 1.0, "source_file": "D:\\Plant Pulse FYP\\lib\\widgets\\weather_header.dart", "source_location": null, "weight": 1.0}, {"source": "d_plant_pulse_fyp_lib_widgets_weather_header_dart", "target": "package_provider_provider_dart", "relation": "imports", "confidence": "EXTRACTED", "confidence_score": 1.0, "source_file": "D:\\Plant Pulse FYP\\lib\\widgets\\weather_header.dart", "source_location": null, "weight": 1.0}, {"source": "d_plant_pulse_fyp_lib_widgets_weather_header_dart", "target": "package_intl_intl_dart", "relation": "imports", "confidence": "EXTRACTED", "confidence_score": 1.0, "source_file": "D:\\Plant Pulse FYP\\lib\\widgets\\weather_header.dart", "source_location": null, "weight": 1.0}, {"source": "d_plant_pulse_fyp_lib_widgets_weather_header_dart", "target": "providers_weather_provider_dart", "relation": "imports", "confidence": "EXTRACTED", "confidence_score": 1.0, "source_file": "D:\\Plant Pulse FYP\\lib\\widgets\\weather_header.dart", "source_location": null, "weight": 1.0}, {"source": "d_plant_pulse_fyp_lib_widgets_weather_header_dart", "target": "models_weather_data_dart", "relation": "imports", "confidence": "EXTRACTED", "confidence_score": 1.0, "source_file": "D:\\Plant Pulse FYP\\lib\\widgets\\weather_header.dart", "source_location": null, "weight": 1.0}, {"source": "d_plant_pulse_fyp_lib_widgets_weather_header_dart", "target": "utils_rice_health_logic_dart", "relation": "imports", "confidence": "EXTRACTED", "confidence_score": 1.0, "source_file": "D:\\Plant Pulse FYP\\lib\\widgets\\weather_header.dart", "source_location": null, "weight": 1.0}]}